neologger/__init__.py
neologger/main.py
neologger/core/Base.py
neologger/core/__init__.py
neologger-1.5.2.dist-info/METADATA
neologger-1.5.2.dist-info/WHEEL
neologger-1.5.2.dist-info/licenses/LICENSE
neologger-1.5.2.dist-info/RECORD
