Metadata-Version: 2.3
Name: neologger
Version: 1.5.2
Summary: NeoLogger is a versatile Python library that simplifies and enhances logging and notifications in your applications. It seamlessly integrates with Slack and Microsoft Teams for real-time notifications and supports broadcasting messages over the STOMP protocol. It incorporates advanced logging and notification features, saving you development time and effort. Now includes a Stopwatch class to track function execution times with precision and an Alarm class to raise notifications when thr
Project-URL: Homepage, https://github.com/neolink3891/NeoLogger
Project-URL: Source, https://github.com/neolink3891/NeoLogger
Project-URL: Issues, https://github.com/neolink3891/NeoLogger/issues
Project-URL: LinkedIn (Pablo Martinez), https://www.linkedin.com/in/orlando-martinez-2649051aa
Project-URL: LinkedIn (Matt Sullivan), https://www.linkedin.com/in/matthewjamessullivan
Project-URL: X, https://x.com/neolink3891
Project-URL: Medium, https://medium.com/@neolink3891
Author-email: Pablo Martinez <neolink3891@gmail.com>, Matt Sullivan <mattys940@gmail.com>
License: MIT License
Keywords: Discord,Microsoft Teams,STOMP,Slack,logging,monitoring,notifications,performance
Classifier: License :: OSI Approved :: MIT License
Classifier: Operating System :: OS Independent
Classifier: Programming Language :: Python :: 3
Requires-Python: >=3.9
Requires-Dist: requests
Requires-Dist: stomp-py
